yelpapi/__init__.py
yelpapi/yelpapi.py
yelpapi-2.5.0.dist-info/AUTHORS.md
yelpapi-2.5.0.dist-info/LICENSE
yelpapi-2.5.0.dist-info/METADATA
yelpapi-2.5.0.dist-info/WHEEL
yelpapi-2.5.0.dist-info/top_level.txt
yelpapi-2.5.0.dist-info/RECORD
