Metadata-Version: 2.1
Name: yelpapi
Version: 2.5.0
Summary: yelpapi is a pure Python implementation of the Yelp Fusion API.
Home-page: https://github.com/lanl/yelpapi
Author: Geoffrey Fairchild
Author-email: mail@gfairchild.com
Maintainer: Geoffrey Fairchild
Maintainer-email: mail@gfairchild.com
License: BSD 3-Clause License
Classifier: Development Status :: 5 - Production/Stable
Classifier: Intended Audience :: Developers
Classifier: License :: OSI Approved :: BSD License
Classifier: Operating System :: OS Independent
Classifier: Programming Language :: Python :: 3
Classifier: Programming Language :: Python :: 3.7
Classifier: Programming Language :: Python :: 3.8
Classifier: Programming Language :: Python :: 3.9
Classifier: Programming Language :: Python :: 3.10
Classifier: Topic :: Internet :: WWW/HTTP :: Dynamic Content
Classifier: Topic :: Software Development :: Libraries :: Python Modules
License-File: LICENSE
License-File: AUTHORS.md
Requires-Dist: requests
